COPYING
__init__.py
phase.py
phase_test.py
setup.py
study.egg-info/PKG-INFO
study.egg-info/SOURCES.txt
study.egg-info/dependency_links.txt
study.egg-info/requires.txt
study.egg-info/top_level.txt