Metadata-Version: 1.0
Name: study
Version: 0.1.0
Summary: Framework for building data studies in a pipe-and-filter style that abstracts over issues such as multiprocessing.
Home-page: http://code.google.com/p/python-study/
Author: Alexander Lamaison
Author-email: awl03@doc.ic.ac.uk
License: GPL3
Download-URL: http://python-study.googlecode.com/svn/trunk/#egg=study-dev
Platform: UNKNOWN
Classifier: Development Status :: 3 - Alpha
Classifier: Intended Audience :: Developers
Classifier: Intended Audience :: Information Technology
Classifier: Intended Audience :: Science/Research
Classifier: License :: OSI Approved :: GNU General Public License (GPL)
Classifier: Operating System :: OS Independent
Classifier: Programming Language :: Python
Classifier: Programming Language :: Python :: 2.5
Classifier: Programming Language :: Python :: 2.6
Classifier: Topic :: Scientific/Engineering
Classifier: Topic :: Scientific/Engineering :: Information Analysis
Classifier: Topic :: Software Development
Classifier: Topic :: Software Development :: Libraries
Classifier: Topic :: Software Development :: Libraries :: Python Modules
